{
    "Group": {
        "Group Name": "ECN Fansub",
        "Short Name": "ECN",
        "IRC": "",
        "Primary Language": "Brazilian Portuguese",
        "Member Opinions And Votes": {
            "Users Approve": "5",
            "Users Disapprove": "24",
            "Total": "29"
        }
    },
    "Subbed Projects": [
        {
            "Show Name": "Bakemono no Ko",
            "Show Type": "Movie - 1 episodes",
            "User Approval": "3 of 6 users approve, 1 comments",
            "Comments": {
                "Good Comments": [
                    "master piece sub"
                ],
                "Bad Comments": []
            }
        },
        {
            "Show Name": "Beyblade Burst",
            "Show Type": "TV - 51 episodes",
            "User Approval": "0 of 2 users approve",
            "Comments": {
                "Good Comments": [],
                "Bad Comments": []
            }
        },
        {
            "Show Name": "Danna ga Nani wo Itteiru ka Wakaranai Ken",
            "Show Type": "TV - 13 episodes",
            "User Approval": "0 of 2 users approve",
            "Comments": {
                "Good Comments": [],
                "Bad Comments": []
            }
        },
        {
            "Show Name": "Endride",
            "Show Type": "TV - 24 episodes",
            "User Approval": "0 of 2 users approve",
            "Comments": {
                "Good Comments": [],
                "Bad Comments": []
            }
        },
        {
            "Show Name": "Jie Mo Ren",
            "Show Type": "ONA - 14 episodes",
            "User Approval": "1 of 3 users approve",
            "Comments": {
                "Good Comments": [],
                "Bad Comments": []
            }
        },
        {
            "Show Name": "Keijo!!!!!!!!",
            "Show Type": "TV - 12 episodes",
            "User Approval": "1 of 3 users approve, 1 comments",
            "Comments": {
                "Good Comments": [
                    "Their subs are for dumb people who can't learn another language"
                ],
                "Bad Comments": []
            }
        },
        {
            "Show Name": "Lance N' Masques",
            "Show Type": "TV - 12 episodes",
            "User Approval": "0 of 2 users approve",
            "Comments": {
                "Good Comments": [],
                "Bad Comments": []
            }
        },
        {
            "Show Name": "Masou Gakuen HxH",
            "Show Type": "TV - 12 episodes",
            "User Approval": "0 of 2 users approve",
            "Comments": {
                "Good Comments": [],
                "Bad Comments": []
            }
        },
        {
            "Show Name": "Ore ga Ojousama Gakkou ni \"Shomin Sample\" Toshite Gets♥Sareta Ken",
            "Show Type": "TV - 12 episodes",
            "User Approval": "0 of 2 users approve",
            "Comments": {
                "Good Comments": [],
                "Bad Comments": []
            }
        },
        {
            "Show Name": "Princess Lover!",
            "Show Type": "TV - 12 episodes",
            "User Approval": "0 of 2 users approve",
            "Comments": {
                "Good Comments": [],
                "Bad Comments": []
            }
        },
        {
            "Show Name": "Princess Lover! OVA",
            "Show Type": "OVA - 2 episodes",
            "User Approval": "0 of 2 users approve",
            "Comments": {
                "Good Comments": [],
                "Bad Comments": []
            }
        },
        {
            "Show Name": "Qualidea Code",
            "Show Type": "TV - 12 episodes",
            "User Approval": "0 of 1 users approve",
            "Comments": {
                "Good Comments": [],
                "Bad Comments": []
            }
        }
    ]
}