{
    "Group": {
        "Group Name": "Last-Subs",
        "Short Name": "Last-Subs",
        "IRC": "",
        "Primary Language": "English",
        "Member Opinions And Votes": {
            "Users Approve": "14",
            "Users Disapprove": "34",
            "Total": "48"
        }
    },
    "Subbed Projects": [
        {
            "Show Name": "Chaos Dragon: Sekiryuu Seneki",
            "Show Type": "TV - 12 episodes",
            "User Approval": "2 of 3 users approve, 2 comments",
            "Comments": {
                "Good Comments": [
                    "yes"
                ],
                "Bad Comments": [
                    "OMG that ENGRISH and 10th episode change of opening and some shit!!!"
                ]
            }
        },
        {
            "Show Name": "Diabolik Lovers OVA",
            "Show Type": "OVA - 1 episodes",
            "User Approval": "3 of 4 users approve",
            "Comments": {
                "Good Comments": [],
                "Bad Comments": []
            }
        },
        {
            "Show Name": "DRAMAtical Murder OVA: Data_xx_Transitory",
            "Show Type": "Special - 1 episodes",
            "User Approval": "1 of 6 users approve, 1 comments",
            "Comments": {
                "Good Comments": [
                    "Which phrases like \"Hurry, us depart hence!\" it'd be very hard to understand without having played the game before watching this."
                ],
                "Bad Comments": []
            }
        },
        {
            "Show Name": "Gintama': Futon ni Haitte kara Buki Nokoshi ni Kizuite Neru ni Nerenai Toki mo Aru",
            "Show Type": "Special - 1 episodes",
            "User Approval": "0 of 1 users approve",
            "Comments": {
                "Good Comments": [],
                "Bad Comments": []
            }
        },
        {
            "Show Name": "Pan de Peace!",
            "Show Type": "TV - 13 episodes",
            "User Approval": "2 of 2 users approve, 1 comments",
            "Comments": {
                "Good Comments": [
                    "Best subs ever"
                ],
                "Bad Comments": []
            }
        },
        {
            "Show Name": "Reikenzan: Hoshikuzu-tachi no Utage",
            "Show Type": "TV - 12 episodes",
            "User Approval": "4 of 12 users approve, 7 comments",
            "Comments": {
                "Good Comments": [
                    "Their translation is so bad it is better to watch the raws.",
                    "The most English out of everything.",
                    "Dropped this one after first few minutes due to really poor translations / guesslations. These peeps need proper translators and editors badly.",
                    "avoid at all costs"
                ],
                "Bad Comments": [
                    "God bless them",
                    "They have absolutely no clue",
                    "The subs are filled with memes and aren't displayed long enough. The size is way too big and it's impossible to watch."
                ]
            }
        },
        {
            "Show Name": "Valkyrie Drive: Mermaid",
            "Show Type": "TV - 12 episodes",
            "User Approval": "4 of 12 users approve, 7 comments",
            "Comments": {
                "Good Comments": [],
                "Bad Comments": []
            }
        },
        {
            "Show Name": "Vampire Holmes",
            "Show Type": "TV - 12 episodes",
            "User Approval": "2 of 20 users approve, 9 comments",
            "Comments": {
                "Good Comments": [
                    "Terrible grammar, hard to understand the meaning.",
                    "Barely literate or understandable; clearly has little knowledge of Japanese or English.",
                    "Fuck what shit this?",
                    "It was read-able",
                    "Shit Google Translate subtitles for a shit show"
                ],
                "Bad Comments": [
                    "Broken English.",
                    "Made a horrible show even more horrible.",
                    "This very seriously.",
                    "Google translate"
                ]
            }
        }
    ]
}