{
    "Group": {
        "Group Name": "Live-eviL & Rice-Box",
        "Short Name": "L-E&R-B",
        "IRC": "",
        "Primary Language": "English",
        "Member Opinions And Votes": {
            "Users Approve": "0",
            "Users Disapprove": "0",
            "Total": "0"
        }
    },
    "Subbed Projects": [
        {
            "Show Name": "Last Exile",
            "Show Type": "TV - 26 episodes",
            "Comments": {
                "Good Comments": [],
                "Bad Comments": []
            }
        }
    ]
}