{
    "Group": {
        "Group Name": "Anime Sols",
        "Short Name": "",
        "IRC": "",
        "Primary Language": "English",
        "Member Opinions And Votes": {
            "Users Approve": "4",
            "Users Disapprove": "1",
            "Total": "5"
        }
    },
    "Subbed Projects": [
        {
            "Show Name": "100-man-nen Chikyuu no Tabi: Bander Book",
            "Show Type": "Special - 1 episodes",
            "User Approval": "1 of 1 users approve",
            "Comments": {
                "Good Comments": [],
                "Bad Comments": []
            }
        },
        {
            "Show Name": "Aoi Blink",
            "Show Type": "TV - 39 episodes",
            "User Approval": "1 of 1 users approve",
            "Comments": {
                "Good Comments": [],
                "Bad Comments": []
            }
        },
        {
            "Show Name": "Black Jack (TV)",
            "Show Type": "TV - 61 episodes",
            "User Approval": "1 of 1 users approve",
            "Comments": {
                "Good Comments": [],
                "Bad Comments": []
            }
        },
        {
            "Show Name": "Bremen 4: Jigoku no Naka no Tenshi-tachi",
            "Show Type": "Special - 1 episodes",
            "User Approval": "1 of 1 users approve",
            "Comments": {
                "Good Comments": [],
                "Bad Comments": []
            }
        },
        {
            "Show Name": "Daishizen no Majuu: Bagi",
            "Show Type": "Movie - 1 episodes",
            "User Approval": "1 of 1 users approve",
            "Comments": {
                "Good Comments": [],
                "Bad Comments": []
            }
        },
        {
            "Show Name": "Fumoon",
            "Show Type": "Special - 1 episodes",
            "User Approval": "1 of 1 users approve",
            "Comments": {
                "Good Comments": [],
                "Bad Comments": []
            }
        },
        {
            "Show Name": "Gokuu no Daibouken",
            "Show Type": "TV - 39 episodes",
            "User Approval": "1 of 1 users approve",
            "Comments": {
                "Good Comments": [],
                "Bad Comments": []
            }
        },
        {
            "Show Name": "Hurricane Polymar",
            "Show Type": "TV - 26 episodes",
            "User Approval": "1 of 1 users approve",
            "Comments": {
                "Good Comments": [],
                "Bad Comments": []
            }
        },
        {
            "Show Name": "Kaitei Choutokkyuu: Marine Express",
            "Show Type": "Special - 1 episodes",
            "User Approval": "1 of 1 users approve",
            "Comments": {
                "Good Comments": [],
                "Bad Comments": []
            }
        },
        {
            "Show Name": "Mahou no Idol Pastel Yumi",
            "Show Type": "TV - 25 episodes",
            "User Approval": "1 of 1 users approve",
            "Comments": {
                "Good Comments": [],
                "Bad Comments": []
            }
        },
        {
            "Show Name": "Mahou no Tenshi Creamy Mami",
            "Show Type": "TV - 52 episodes",
            "User Approval": "1 of 1 users approve, 1 comments",
            "Comments": {
                "Good Comments": [
                    "I could follow the story without being confused reading subs, so thank you."
                ],
                "Bad Comments": []
            }
        },
        {
            "Show Name": "Ninja Senshi Tobikage",
            "Show Type": "TV - 43 episodes",
            "User Approval": "1 of 1 users approve, 1 comments",
            "Comments": {
                "Good Comments": [],
                "Bad Comments": []
            }
        },
        {
            "Show Name": "Oniisama e...",
            "Show Type": "TV - 39 episodes",
            "User Approval": "1 of 1 users approve, 1 comments",
            "Comments": {
                "Good Comments": [],
                "Bad Comments": []
            }
        },
        {
            "Show Name": "Time Bokan Series: Yatterman",
            "Show Type": "TV - 108 episodes",
            "User Approval": "1 of 2 users approve, 2 comments",
            "Comments": {
                "Good Comments": [
                    "Only group that has subbed more than 2 episodes. Unfortunately they dropped it at 17 episodes."
                ],
                "Bad Comments": [
                    "They did an okay job with small mistakes, but they drop series too fast."
                ]
            }
        },
        {
            "Show Name": "Time Slip Ichimannen: Prime Rose",
            "Show Type": "Special - 1 episodes",
            "User Approval": "1 of 2 users approve, 2 comments",
            "Comments": {
                "Good Comments": [],
                "Bad Comments": []
            }
        },
        {
            "Show Name": "Uchuu no Kishi Tekkaman",
            "Show Type": "TV - 26 episodes",
            "User Approval": "1 of 2 users approve, 2 comments",
            "Comments": {
                "Good Comments": [],
                "Bad Comments": []
            }
        },
        {
            "Show Name": "Yatterman",
            "Show Type": "TV - 60 episodes",
            "User Approval": "1 of 2 users approve, 2 comments",
            "Comments": {
                "Good Comments": [
                    "You must pay to watch. Available only for US & Canada"
                ],
                "Bad Comments": []
            }
        }
    ]
}