{
    "Group": {
        "Group Name": "Temuchin",
        "Short Name": "Temuchin",
        "IRC": "",
        "Primary Language": "English",
        "Member Opinions And Votes": {
            "Users Approve": "7",
            "Users Disapprove": "0",
            "Total": "7"
        }
    },
    "Subbed Projects": [
        {
            "Show Name": "Choujin Densetsu Urotsukidouji",
            "Show Type": "OVA - 3 episodes",
            "User Approval": "2 of 2 users approve, 1 comments",
            "Comments": {
                "Good Comments": [
                    "Good work; a few mistakes, but not really anything too bad. Only one available as well, and it does a solid job, definitely archive-worthy."
                ],
                "Bad Comments": []
            }
        },
        {
            "Show Name": "G-Taste (2010)",
            "Show Type": "OVA - 1 episodes",
            "User Approval": "2 of 2 users approve, 1 comments",
            "Comments": {
                "Good Comments": [],
                "Bad Comments": []
            }
        },
        {
            "Show Name": "Macross Plus",
            "Show Type": "OVA - 4 episodes",
            "User Approval": "2 of 2 users approve, 1 comments",
            "Comments": {
                "Good Comments": [],
                "Bad Comments": []
            }
        },
        {
            "Show Name": "Queen Emeraldas",
            "Show Type": "OVA - 4 episodes",
            "User Approval": "1 of 1 users approve",
            "Comments": {
                "Good Comments": [],
                "Bad Comments": []
            }
        },
        {
            "Show Name": "Saint Seiya: Jashin Eris",
            "Show Type": "Movie - 1 episodes",
            "User Approval": "1 of 1 users approve",
            "Comments": {
                "Good Comments": [],
                "Bad Comments": []
            }
        },
        {
            "Show Name": "Saint Seiya: Shinku no Shounen Densetsu",
            "Show Type": "Movie - 1 episodes",
            "User Approval": "1 of 1 users approve",
            "Comments": {
                "Good Comments": [],
                "Bad Comments": []
            }
        },
        {
            "Show Name": "Silent Möbius 2",
            "Show Type": "Movie - 1 episodes",
            "User Approval": "1 of 1 users approve",
            "Comments": {
                "Good Comments": [],
                "Bad Comments": []
            }
        },
        {
            "Show Name": "Silent Möbius: The Motion Picture",
            "Show Type": "Movie - 1 episodes",
            "User Approval": "1 of 1 users approve",
            "Comments": {
                "Good Comments": [],
                "Bad Comments": []
            }
        },
        {
            "Show Name": "Soliton no Akuma",
            "Show Type": "Movie - 1 episodes",
            "User Approval": "1 of 1 users approve",
            "Comments": {
                "Good Comments": [],
                "Bad Comments": []
            }
        },
        {
            "Show Name": "The SoulTaker: Tamashii-gari",
            "Show Type": "TV - 13 episodes",
            "User Approval": "4 of 4 users approve, 1 comments",
            "Comments": {
                "Good Comments": [
                    "most accurate thus far"
                ],
                "Bad Comments": []
            }
        }
    ]
}