{
    "Group": {
        "Group Name": "Kodocha Anime",
        "Short Name": "Kodocha",
        "IRC": "",
        "Primary Language": "English",
        "Member Opinions And Votes": {
            "Users Approve": "0",
            "Users Disapprove": "0",
            "Total": "0"
        }
    },
    "Subbed Projects": [
        {
            "Show Name": "Mainichi ga Nichiyoubi",
            "Show Type": "OVA - 6 episodes",
            "Comments": {
                "Good Comments": [],
                "Bad Comments": []
            }
        }
    ]
}