{
    "Group": {
        "Group Name": "Shinsen-Subs & Mishicorp",
        "Short Name": "Shinsen-Corp",
        "IRC": "Shinsen-Subs@irc.rizon.net",
        "Primary Language": "English",
        "Member Opinions And Votes": {
            "Users Approve": "120",
            "Users Disapprove": "2",
            "Total": "122"
        }
    },
    "Subbed Projects": [
        {
            "Show Name": "Heroic Age",
            "Show Type": "TV - 26 episodes",
            "User Approval": "42 of 43 users approve, 10 comments",
            "Comments": {
                "Good Comments": [
                    "It's just an all around good sub.",
                    "They're slow, but are continuing on with the show when no one else would. Thanks guys.",
                    "The only ones who still seem to be subbing this show.",
                    "It's Shinsen. Good. And they finished the show.",
                    "Good, wish there was an HD version.."
                ],
                "Bad Comments": [
                    "great subs. No spelling or grammar errors.",
                    "null",
                    "Excellent.",
                    "undefined",
                    "Becouse you can actualy get them fast"
                ]
            }
        },
        {
            "Show Name": "Zombie-Loan",
            "Show Type": "TV - 11 episodes",
            "User Approval": "78 of 79 users approve, 16 comments",
            "Comments": {
                "Good Comments": [
                    "Good quality and it doesn't take them long to sub it either.",
                    "both sub groups always work magic and combines they manage great translation without overdoing the effect of type of the subtitles.",
                    "awesome",
                    "Great Translation, Great Type Setting, Easy too follow.",
                    "Great subs, practically zero errors.",
                    "They did a great job at subbing Zombie Loan.",
                    "translations in some parts were completely off, OP/ED subtitle animation distracting",
                    "Good subs and video for this anime."
                ],
                "Bad Comments": [
                    "just love it",
                    "They get thier subs out quickly, but the subs are still quality.",
                    "Very clear subtitles, episodes used are great quality.",
                    "Shinsen-Corp the fastest and still well-subbed option for Zombie Loan.",
                    "Great quality and fast.",
                    "all the episodes are great quality and actual english subs",
                    "Good quality subs",
                    "I found it clear."
                ]
            }
        }
    ]
}