{
    "Group": {
        "Group Name": "SonoTooriDesu Fansub",
        "Short Name": "STD Fansub",
        "IRC": "",
        "Primary Language": "Brazilian Portuguese",
        "Member Opinions And Votes": {
            "Users Approve": "0",
            "Users Disapprove": "0",
            "Total": "0"
        }
    },
    "Subbed Projects": [
        {
            "Show Name": "Harmonie",
            "Show Type": "Movie - 1 episodes",
            "Comments": {
                "Good Comments": [],
                "Bad Comments": []
            }
        }
    ]
}