{
    "Group": {
        "Group Name": "MovingLines",
        "Short Name": "MovingLines",
        "IRC": "",
        "Primary Language": "English",
        "Member Opinions And Votes": {
            "Users Approve": "1",
            "Users Disapprove": "1",
            "Total": "2"
        }
    },
    "Subbed Projects": [
        {
            "Show Name": "Omoi no Kakera",
            "Show Type": "Special - 1 episodes",
            "User Approval": "0 of 1 users approve",
            "Comments": {
                "Good Comments": [],
                "Bad Comments": []
            }
        },
        {
            "Show Name": "Sakura Internet",
            "Show Type": "ONA - 1 episodes",
            "User Approval": "1 of 1 users approve",
            "Comments": {
                "Good Comments": [],
                "Bad Comments": []
            }
        }
    ]
}